gapms/__init__.py
gapms/extract.py
gapms/filter.py
gapms/gtf_utils.py
gapms/main.py
gapms/mapping_utils.py
gapms/model_utils.py
gapms/peptide_utils.py
gapms/plotting.py
gapms/tools.py
gapms/translate.py
gapms-0.1.3.dist-info/licenses/LICENSE
gapms-0.1.3.dist-info/METADATA
gapms-0.1.3.dist-info/WHEEL
gapms-0.1.3.dist-info/entry_points.txt
gapms-0.1.3.dist-info/top_level.txt
gapms-0.1.3.dist-info/RECORD
