Metadata-Version: 2.4
Name: gapms
Version: 0.1.3
Summary: GAP-MS is a pipeline designed to evaluate and refine predicted gene models by integrating proteogenomic evidence from mass spectrometry with in-silico gene predictions.
Author-email: Qussai Abbas <qussai.abbas@tum.de>
Requires-Python: <3.11,>=3.10
License-File: LICENSE
Requires-Dist: pandas==2.2.3
Requires-Dist: matplotlib==3.8.3
Requires-Dist: numpy==1.24.4
Requires-Dist: seaborn==0.12.2
Requires-Dist: biopython==1.83
Requires-Dist: scipy==1.12.0
Requires-Dist: scikit-learn==1.4.1.post1
Requires-Dist: xgboost==2.0.3
Requires-Dist: shap==0.46.0
Requires-Dist: psauron==1.0.4
Dynamic: license-file
